kartei/__init__.py
kartei/entry.py
kartei-0.1.0.dist-info/LICENSE
kartei-0.1.0.dist-info/METADATA
kartei-0.1.0.dist-info/WHEEL
kartei-0.1.0.dist-info/entry_points.txt
kartei-0.1.0.dist-info/RECORD
