Metadata-Version: 2.1
Name: kartei
Version: 0.1.0
Summary: Kartei is a simple, CLI-based vocabulary trainer.
License: MIT
Author: Marc Berndtgen
Author-email: marc@berndtgen.org
Requires-Python: >=3.8,<4.0
Classifier: License :: OSI Approved :: MIT License
Classifier: Programming Language :: Python :: 3
Classifier: Programming Language :: Python :: 3.8
Classifier: Programming Language :: Python :: 3.9
Classifier: Programming Language :: Python :: 3.10
Classifier: Programming Language :: Python :: 3.11
Classifier: Programming Language :: Python :: 3.12
